prokbert/__init__.py
ProkBERT_base_test_library-0.0.1.dist-info/LICENSE
ProkBERT_base_test_library-0.0.1.dist-info/METADATA
ProkBERT_base_test_library-0.0.1.dist-info/WHEEL
ProkBERT_base_test_library-0.0.1.dist-info/top_level.txt
ProkBERT_base_test_library-0.0.1.dist-info/RECORD
