Metadata-Version: 2.1
Name: ProkBERT-base-test-library
Version: 0.0.1
Summary: A brief description of your library
Author: gfgfgf
Author-email: obalasz@gmail.com
License-File: LICENSE
